tileorm/__init__.py
tileorm/exceptions.py
tileorm/fields.py
tileorm/model.py
tileorm/types.py
tileorm-0.1.3.dist-info/LICENSE
tileorm-0.1.3.dist-info/METADATA
tileorm-0.1.3.dist-info/WHEEL
tileorm-0.1.3.dist-info/RECORD
