Metadata-Version: 2.1
Name: tileorm
Version: 0.1.3
Summary: An ORM for Tile38 inspired by Peewee - with Pydantic validation
License: MIT
Author: Alex Ward
Author-email: alxwrd@googlemail.com
Requires-Python: >=3.12,<4.0
Classifier: License :: OSI Approved :: MIT License
Classifier: Programming Language :: Python :: 3
Classifier: Programming Language :: Python :: 3.12
Classifier: Programming Language :: Python :: 3.13
Requires-Dist: pydantic (>=2.9.2,<3.0.0)
Requires-Dist: pyle38 (>=0.14.2,<0.15.0)
